setup.cfg
setup.py
Flask_DropIn.egg-info/PKG-INFO
Flask_DropIn.egg-info/SOURCES.txt
Flask_DropIn.egg-info/dependency_links.txt
Flask_DropIn.egg-info/entry_points.txt
Flask_DropIn.egg-info/not-zip-safe
Flask_DropIn.egg-info/requires.txt
Flask_DropIn.egg-info/top_level.txt
flask_dropin/__init__.py
flask_dropin/nameddrops.py